cortexquest/__init__.py
cortexquest/cli.py
cortexquest/core/__init__.py
cortexquest/core/data_manager.py
cortexquest/core/google_auth.py
cortexquest/core/sheet_loader.py
cortexquest/core/translator.py
cortexquest/cortexquest.py
cortexquest-0.1.0.dist-info/AUTHORS.rst
cortexquest-0.1.0.dist-info/LICENSE
cortexquest-0.1.0.dist-info/METADATA
cortexquest-0.1.0.dist-info/WHEEL
cortexquest-0.1.0.dist-info/entry_points.txt
cortexquest-0.1.0.dist-info/RECORD
