Metadata-Version: 2.1
Name: cortexquest
Version: 0.1.0
Summary: CortexQuest is a Python package designed to facilitate the reading, parsing, and analysis of questionnaires hosted on Google Sheets, specifically tailored for brain bank data. This tool aims to streamline the process of handling survey data related to neuroscience research, providing researchers with an efficient and user-friendly way to manage and analyze their data.
Home-page: https://github.com/GalKepler/CortexQuest
License: MIT
Keywords: neuroscience,brain bank,google sheets,survey,analysis
Author: Gal Kepler
Author-email: galkepler@gmail.com
Requires-Python: >=3.10,<4.0
Classifier: Development Status :: 3 - Alpha
Classifier: Intended Audience :: Science/Research
Classifier: License :: OSI Approved :: MIT License
Classifier: Programming Language :: Python :: 3
Classifier: Programming Language :: Python :: 3.10
Classifier: Programming Language :: Python :: 3.11
Classifier: Programming Language :: Python :: 3.12
Classifier: Topic :: Scientific/Engineering :: Information Analysis
Requires-Dist: bump2version (>=1.0.1,<2.0.0)
Requires-Dist: chardet (>=5.2.0,<6.0.0)
Requires-Dist: google-auth (>=2.29.0,<3.0.0)
Requires-Dist: google-auth-oauthlib (>=1.2.0,<2.0.0)
Requires-Dist: gspread (>=6.1.2,<7.0.0)
Requires-Dist: ipykernel (>=6.29.4,<7.0.0)
Requires-Dist: oauth2client (>=4.1.3,<5.0.0)
Requires-Dist: pandas (>=2.2.2,<3.0.0)
Requires-Dist: pre-commit (>=3.7.1,<4.0.0)
Requires-Dist: sphinx (>=7.3.7,<8.0.0)
Requires-Dist: tox (>=4.15.0,<5.0.0)
Requires-Dist: translate (>=3.6.1,<4.0.0)
Requires-Dist: twine (>=5.1.0,<6.0.0)
Requires-Dist: typer (>=0.12.0,<0.13.0)
Requires-Dist: wheel (>=0.43.0,<0.44.0)
Project-URL: Documentation, https://github.com/GalKepler/CortexQuest
Project-URL: Repository, https://github.com/GalKepler/CortexQuest
